datapackage_pipelines_goodtables/VERSION
datapackage_pipelines_goodtables/__init__.py
datapackage_pipelines_goodtables/processors/__init__.py
datapackage_pipelines_goodtables/processors/validate.py
datapackage_pipelines_goodtables-0.0.2a0.dist-info/DESCRIPTION.rst
datapackage_pipelines_goodtables-0.0.2a0.dist-info/METADATA
datapackage_pipelines_goodtables-0.0.2a0.dist-info/RECORD
datapackage_pipelines_goodtables-0.0.2a0.dist-info/WHEEL
datapackage_pipelines_goodtables-0.0.2a0.dist-info/metadata.json
datapackage_pipelines_goodtables-0.0.2a0.dist-info/top_level.txt
