Metadata-Version: 2.0
Name: datapackage-pipelines-goodtables
Version: 0.0.2a0
Summary: {{ DESCRIPTION }}
Home-page: https://github.com/frictionlessdata/datapackage_pipelines_goodtables
Author: Open Knowledge International
Author-email: UNKNOWN
License: MIT
Keywords: data
Platform: UNKNOWN
Classifier: Development Status :: 3 - Alpha
Classifier: Environment :: Web Environment
Classifier: Intended Audience :: Developers
Classifier: License :: OSI Approved :: MIT License
Classifier: Operating System :: OS Independent
Classifier: Programming Language :: Python :: 3.6
Classifier: Topic :: Internet :: WWW/HTTP :: Dynamic Content
Classifier: Topic :: Software Development :: Libraries :: Python Modules
Requires-Dist: datapackage-pipelines (>=1.0,<2.0)
Requires-Dist: goodtables
Provides-Extra: develop
Requires-Dist: pylama; extra == 'develop'
Requires-Dist: tox; extra == 'develop'
